naylence/fame/core/__init__.py
naylence/fame/core/address/__init__.py
naylence/fame/core/address/address.py
naylence/fame/core/address/addressable.py
naylence/fame/core/channel/__init__.py
naylence/fame/core/channel/binding.py
naylence/fame/core/channel/channel.py
naylence/fame/core/connector/__init__.py
naylence/fame/core/connector/connector.py
naylence/fame/core/connector/connector_state.py
naylence/fame/core/fame_config.py
naylence/fame/core/fame_fabric.py
naylence/fame/core/fame_fabric_config.py
naylence/fame/core/fame_fabric_factory.py
naylence/fame/core/handlers/__init__.py
naylence/fame/core/handlers/handlers.py
naylence/fame/core/protocol/__init__.py
naylence/fame/core/protocol/channel_message.py
naylence/fame/core/protocol/delivery_context.py
naylence/fame/core/protocol/envelope.py
naylence/fame/core/protocol/flow.py
naylence/fame/core/protocol/frames.py
naylence/fame/core/protocol/origin_type.py
naylence/fame/core/protocol/response_type.py
naylence/fame/core/protocol/security_header.py
naylence/fame/core/protocol/security_settings.py
naylence/fame/core/protocol/sender.py
naylence/fame/core/rpc/jsonrpc.py
naylence/fame/core/rpc/types.py
naylence/fame/core/service/__init__.py
naylence/fame/core/service/capabilities.py
naylence/fame/core/service/fame_service.py
naylence/fame/core/service/subscription.py
naylence/fame/core/util/__init__.py
naylence/fame/core/util/base_config.py
naylence/fame/core/util/closeable.py
naylence/fame/core/util/constants.py
naylence/fame/core/util/id_generator.py
naylence/fame/core/util/repr.py
naylence_core-0.3.3.dist-info/METADATA
naylence_core-0.3.3.dist-info/WHEEL
naylence_core-0.3.3.dist-info/licenses/LICENSE
naylence_core-0.3.3.dist-info/RECORD
